epitopegen/__init__.py
epitopegen/analyze_antigen.py
epitopegen/analyze_ce.py
epitopegen/analyze_deg.py
epitopegen/analyze_pa.py
epitopegen/analyze_pre.py
epitopegen/annotate.py
epitopegen/config.py
epitopegen/inference.py
epitopegen/resources/tokenizer/GPT2Config_small.pkl
epitopegen/resources/tokenizer/config.json
epitopegen/resources/tokenizer/tokenizer.json
epitopegen-0.1.0.dist-info/METADATA
epitopegen-0.1.0.dist-info/WHEEL
epitopegen-0.1.0.dist-info/top_level.txt
epitopegen-0.1.0.dist-info/RECORD
