Metadata-Version: 2.2
Name: epitopegen
Version: 0.1.0
Summary: epitopegen: TCR-based epitope sequence prediction
Author-email: Minuk Ma <minukma@cs.ubc.ca>
Requires-Python: >=3.8
Requires-Dist: torch>=1.10.0
Requires-Dist: transformers>=4.0.0
Requires-Dist: pandas>=1.0.0
Requires-Dist: numpy>=1.19.0
Requires-Dist: Levenshtein==0.25.1
Requires-Dist: matplotlib==3.7.3
Requires-Dist: seaborn==0.13.2
Requires-Dist: scanpy==1.10.3
Requires-Dist: biopython==1.83
